{
  "run": {
    "command": "nx build admin --configuration=production --skip-nx-cache",
    "startTime": "2026-06-21T15:22:03.067Z",
    "endTime": "2026-06-21T15:22:27.722Z",
    "inner": false
  },
  "tasks": [
    {
      "taskId": "admin:build:production",
      "target": "build",
      "projectName": "admin",
      "hash": "18106629510965433362",
      "startTime": "2026-06-21T15:22:03.148Z",
      "endTime": "2026-06-21T15:22:27.702Z",
      "params": "",
      "cacheStatus": "cache-miss",
      "status": 0
    }
  ]
}